pyCast_USGS-4.0.2.dist-info/DESCRIPTION.rst
pyCast_USGS-4.0.2.dist-info/METADATA
pyCast_USGS-4.0.2.dist-info/RECORD
pyCast_USGS-4.0.2.dist-info/WHEEL
pyCast_USGS-4.0.2.dist-info/metadata.json
pyCast_USGS-4.0.2.dist-info/top_level.txt
shakecast/__init__.py
shakecast/__main__.py
shakecast/build_update.py
shakecast/admin/__init__.py
shakecast/admin/Linux/__init__.py
shakecast/admin/Linux/pycast_watcher.sh
shakecast/admin/Linux/restart_shakecast.sh
shakecast/admin/Linux/server_service.py
shakecast/admin/Linux/start_shakecast.sh
shakecast/admin/Linux/stop_shakecast.sh
shakecast/admin/Linux/web_server_service.py
shakecast/admin/Windows/__init__.py
shakecast/admin/Windows/env_setup.cmd
shakecast/admin/Windows/restart_shakecast.cmd
shakecast/admin/Windows/server_service.py
shakecast/admin/Windows/start_shakecast.cmd
shakecast/admin/Windows/stop_shakecast.cmd
shakecast/admin/Windows/uninstall_shakecast_services.cmd
shakecast/admin/Windows/web_server_service.py
shakecast/sc/__init__.py
shakecast/sc/ui.py
shakecast/sc/ui.pyc
shakecast/sc/web_server.py
shakecast/sc/web_server.pyc
shakecast/sc/app/__init__.py
shakecast/sc/app/__init__.pyc
shakecast/sc/app/db_migrations.py
shakecast/sc/app/functions.py
shakecast/sc/app/functions.pyc
shakecast/sc/app/newthread.py
shakecast/sc/app/newthread.pyc
shakecast/sc/app/objects.py
shakecast/sc/app/objects.pyc
shakecast/sc/app/orm.py
shakecast/sc/app/orm.pyc
shakecast/sc/app/sc_config.py
shakecast/sc/app/server.py
shakecast/sc/app/server.pyc
shakecast/sc/app/task.py
shakecast/sc/app/task.pyc
shakecast/sc/app/util.py
shakecast/sc/app/util.pyc
shakecast/sc/app/plugins/.keep
shakecast/sc/app/plugins/__init__.py
shakecast/sc/conf/#sc.json#
shakecast/sc/conf/.keep
shakecast/sc/conf/__init__.py
shakecast/sc/conf/sc.json
shakecast/sc/conf/sc.json~
shakecast/sc/data/.keep
shakecast/sc/data/ak15819827/image.png
shakecast/sc/data/ak15819827/ak15819827-3/grid.xml
shakecast/sc/data/ak15819827/ak15819827-3/ii_overlay.png
shakecast/sc/data/ak15819827/ak15819827-3/intensity.jpg
shakecast/sc/data/ak15819827/ak15819827-3/stationlist.xml
shakecast/sc/data/ak15820028/image.png
shakecast/sc/data/heartbeat/image.png
shakecast/sc/view/app/shakecast-admin/pages/facilities/facility-info/facility-info.component.css
shakecast/sc/view/app/shakecast-admin/pages/facilities/facility-info/facility-info.component.html
shakecast/sc/view/app/shakecast-admin/pages/facilities/facility-info/facility-info.component.ts
shakecast/sc/web_src/src/app/shakecast-admin/pages/facilities/facility-info/facility-info.component.css
shakecast/sc/web_src/src/app/shakecast-admin/pages/facilities/facility-info/facility-info.component.html
shakecast/sc/web_src/src/app/shakecast-admin/pages/facilities/facility-info/facility-info.component.ts
