Metadata-Version: 2.0
Name: pyCast-USGS
Version: 4.0.2
Summary: Real time notifications to aid in post earthquake recovery
Home-page: https://github.com/usgs/shakecast
Author: Daniel Slosky
Author-email: danielslosky@gmail.com
License: MIT
Keywords: shakecast pycast earthquake earthquakes geology
Platform: UNKNOWN
Classifier: Development Status :: 4 - Beta
Classifier: Intended Audience :: Developers
Classifier: Intended Audience :: End Users/Desktop
Classifier: Topic :: Scientific/Engineering
Classifier: License :: OSI Approved :: MIT License
Classifier: Programming Language :: Python :: 2.7
Requires-Dist: Flask (==0.10.1)
Requires-Dist: Flask-Login (==0.3.2)
Requires-Dist: Flask-Uploads (==0.2.0)
Requires-Dist: Jinja2 (==2.8)
Requires-Dist: MarkupSafe (==0.23)
Requires-Dist: PySocks (==1.5.7)
Requires-Dist: SQLAlchemy (==1.0.14)
Requires-Dist: Werkzeug (==0.11.10)
Requires-Dist: click (==6.6)
Requires-Dist: itsdangerous (==0.24)
Requires-Dist: wheel (==0.26.0)
Requires-Dist: xmltodict (==0.10.2)
